CHANGELOG.txt
MANIFEST.in
README.rst
TERMS.txt
requirements.txt
setup.py
bin/hmda_create_schemas
bin/hmda_extract_geo_data
bin/hmda_load_cbsa
bin/hmda_load_code_sheet
bin/hmda_load_geo
docs/Makefile
docs/conf.py
docs/creating_databases.rst
docs/index.rst
docs/loading_data.rst
docs/api/hmda_tools.data.rst
docs/api/hmda_tools.rst
docs/api/modules.rst
hmda_tools/__init__.py
hmda_tools/__init__.pyc
hmda_tools/unicode_csv.py
hmda_tools/unicode_csv.pyc
hmda_tools.egg-info/PKG-INFO
hmda_tools.egg-info/SOURCES.txt
hmda_tools.egg-info/dependency_links.txt
hmda_tools.egg-info/not-zip-safe
hmda_tools.egg-info/requires.txt
hmda_tools.egg-info/top_level.txt
hmda_tools/code_sheets/action_taken.csv
hmda_tools/code_sheets/agency.csv
hmda_tools/code_sheets/counties.csv
hmda_tools/code_sheets/denial_reason.csv
hmda_tools/code_sheets/edit_status.csv
hmda_tools/code_sheets/ethnicity.csv
hmda_tools/code_sheets/hoepa.csv
hmda_tools/code_sheets/lien_status.csv
hmda_tools/code_sheets/loan_purpose.csv
hmda_tools/code_sheets/loan_type.csv
hmda_tools/code_sheets/owner_occupancy.csv
hmda_tools/code_sheets/preapproval.csv
hmda_tools/code_sheets/property_type.csv
hmda_tools/code_sheets/purchaser_type.csv
hmda_tools/code_sheets/race.csv
hmda_tools/code_sheets/sex.csv
hmda_tools/code_sheets/tracts.csv
hmda_tools/data/__init__.py
hmda_tools/data/cbsa.py
hmda_tools/data/geo.py
hmda_tools/data/schemas.py