Metadata-Version: 1.1
Name: hmda-tools
Version: 0.1.4
Summary: Tools to make working with HMDA data easier.
Home-page: http://github.com/cfpb/hmda-tools
Author: Clinton Dreisbach and others
Author-email: clinton.dreisbach@cfpb.gov
License: Public domain
Platform: UNKNOWN
Classifier: Development Status :: 3 - Alpha
Classifier: Environment :: Console
Classifier: License :: Public Domain
Classifier: Programming Language :: Python
